CHANGES.txt
CONTRIBUTORS.txt
LICENSE
MANIFEST.in
README.rst
setup.cfg
setup.py
./ZPsycopgDA/DA.py
./ZPsycopgDA/__init__.py
./ZPsycopgDA/db.py
./ZPsycopgDA/pool.py
ZPsycopgDA.egg-info/PKG-INFO
ZPsycopgDA.egg-info/SOURCES.txt
ZPsycopgDA.egg-info/dependency_links.txt
ZPsycopgDA.egg-info/entry_points.txt
ZPsycopgDA.egg-info/namespace_packages.txt
ZPsycopgDA.egg-info/not-zip-safe
ZPsycopgDA.egg-info/requires.txt
ZPsycopgDA.egg-info/top_level.txt
ZPsycopgDA/dtml/add.dtml
ZPsycopgDA/dtml/browse.dtml
ZPsycopgDA/dtml/edit.dtml
ZPsycopgDA/dtml/table_info.dtml
ZPsycopgDA/icons/DBAdapterFolder_icon.gif
ZPsycopgDA/icons/bin.gif
ZPsycopgDA/icons/date.gif
ZPsycopgDA/icons/datetime.gif
ZPsycopgDA/icons/field.gif
ZPsycopgDA/icons/float.gif
ZPsycopgDA/icons/int.gif
ZPsycopgDA/icons/stable.gif
ZPsycopgDA/icons/table.gif
ZPsycopgDA/icons/text.gif
ZPsycopgDA/icons/time.gif
ZPsycopgDA/icons/view.gif
ZPsycopgDA/icons/what.gif