Metadata-Version: 1.0
Name: ZPsycopgDA
Version: 2.4.6
Summary: Zope bindings for psycopg2.
Home-page: http://initd.org/psycopg/
Author: Federico Di Gregorio
Author-email: fog@initd.org
License: GPL with exceptions or ZPL
Platform: UNKNOWN
Classifier: Development Status :: 5 - Production/Stable
Classifier: Programming Language :: Python
Classifier: Framework :: Zope2
Classifier: License :: OSI Approved :: GNU Library or Lesser General Public License (LGPL)
Classifier: Topic :: Database
